eqldata/__init__.py
eqldata/__version__.py
eqldata/client.py
eqldata-1.6.dist-info/LICENSE.txt
eqldata-1.6.dist-info/METADATA
eqldata-1.6.dist-info/WHEEL
eqldata-1.6.dist-info/top_level.txt
eqldata-1.6.dist-info/RECORD
