Metadata-Version: 2.1
Name: eqldata
Version: 1.6
Summary: The official Python client for the Eql RT Data
Home-page: https://equalsolution.com
Author: Equalsolution
Author-email: info@equalsolution.com
License: MIT
Classifier: Intended Audience :: Developers
Classifier: Intended Audience :: Financial and Insurance Industry
Classifier: Programming Language :: Python
Classifier: Natural Language :: English
Classifier: License :: OSI Approved :: MIT License
Classifier: Programming Language :: Python :: 3.9
Classifier: Topic :: Office/Business :: Financial :: Investment
Classifier: Topic :: Software Development :: Libraries :: Python Modules
Classifier: Topic :: Software Development :: Libraries
License-File: LICENSE.txt
Requires-Dist: websocket-client
Requires-Dist: requests
